{"commitInfo":{"timestamp":1708373233610,"operation":"MERGE","operationParameters":{"predicate":"[\"((city#3952 = city#3885) AND (date#3932 = date#3844))\"]","matchedPredicates":"[]","notMatchedPredicates":"[{\"actionType\":\"insert\"}]","notMatchedBySourcePredicates":"[]"},"readVersion":3,"isolationLevel":"Serializable","isBlindAppend":false,"operationMetrics":{"numTargetRowsCopied":"0","numTargetRowsDeleted":"0","numTargetFilesAdded":"1","numTargetBytesAdded":"210549","numTargetBytesRemoved":"0","numTargetRowsMatchedUpdated":"0","executionTimeMs":"744","numTargetRowsInserted":"2534","numTargetRowsMatchedDeleted":"0","scanTimeMs":"0","numTargetRowsUpdated":"0","numOutputRows":"2534","numTargetRowsNotMatchedBySourceUpdated":"0","numTargetChangeFilesAdded":"0","numSourceRows":"2534","numTargetFilesRemoved":"0","numTargetRowsNotMatchedBySourceDeleted":"0","rewriteTimeMs":"739"},"engineInfo":"Apache-Spark/3.5.0 Delta-Lake/3.0.0","txnId":"152807d1-db59-418e-8131-6c3c3f3fe255"}}
{"add":{"path":"part-00000-afb279d2-e5c2-429c-ad22-9bbf9d7a002b-c000.snappy.parquet","partitionValues":{},"size":210549,"modificationTime":1708373233600,"dataChange":true,"stats":"{\"numRecords\":2534,\"minValues\":{\"id\":0,\"date\":\"2016-12-31T23:00:00.000+01:00\",\"weather_code\":0.0,\"temperature_2m_max\":-7.2695,\"temperature_2m_min\":-14.9695,\"temperature_2m_mean\":-10.2695,\"apparent_temperature_max\":-14.380255,\"apparent_temperature_min\":-20.452946,\"apparent_temperature_mean\":-15.595165,\"sunrise\":0,\"sunset\":0,\"daylight_duration\":27518.523,\"sunshine_duration\":0.0,\"precipitation_sum\":0.0,\"rain_sum\":0.0,\"snowfall_sum\":0.0,\"precipitation_hours\":0.0,\"wind_speed_10m_max\":7.10031,\"wind_gusts_10m_max\":12.24,\"wind_direction_10m_dominant\":0.08498608,\"shortwave_radiation_sum\":0.29,\"city\":\"London\"},\"maxValues\":{\"id\":2533,\"date\":\"2023-12-08T23:00:00.000+01:00\",\"weather_code\":75.0,\"temperature_2m_max\":37.6305,\"temperature_2m_min\":23.6805,\"temperature_2m_mean\":29.972166,\"apparent_temperature_max\":37.18923,\"apparent_temperature_min\":25.084702,\"apparent_temperature_mean\":29.607391,\"sunrise\":0,\"sunset\":0,\"daylight_duration\":60622.312,\"sunshine_duration\":55586.05,\"precipitation_sum\":108.2,\"rain_sum\":108.2,\"snowfall_sum\":7.42,\"precipitation_hours\":24.0,\"wind_speed_10m_max\":60.15879,\"wind_gusts_10m_max\":111.24,\"wind_direction_10m_dominant\":359.99997,\"shortwave_radiation_sum\":29.36,\"city\":\"London\"},\"nullCount\":{\"id\":0,\"date\":0,\"weather_code\":0,\"temperature_2m_max\":0,\"temperature_2m_min\":0,\"temperature_2m_mean\":1,\"apparent_temperature_max\":0,\"apparent_temperature_min\":0,\"apparent_temperature_mean\":1,\"sunrise\":0,\"sunset\":0,\"daylight_duration\":0,\"sunshine_duration\":1,\"precipitation_sum\":1,\"rain_sum\":1,\"snowfall_sum\":1,\"precipitation_hours\":0,\"wind_speed_10m_max\":0,\"wind_gusts_10m_max\":0,\"wind_direction_10m_dominant\":1,\"shortwave_radiation_sum\":1,\"city\":0}}"}}
